sampletestlohit/__init__.py
testversionlohit-0.1.0.dist-info/METADATA
testversionlohit-0.1.0.dist-info/WHEEL
testversionlohit-0.1.0.dist-info/top_level.txt
testversionlohit-0.1.0.dist-info/RECORD
