Metadata-Version: 2.1
Name: testversionlohit
Version: 0.1.0
Summary: My first Python package
Author: lohit
Author-email: lohit.cs19@bitsathy.ac.in
License: UNKNOWN
Keywords: python,lohit,lohitpackage
Platform: UNKNOWN
Classifier: Development Status :: 3 - Alpha
Classifier: Intended Audience :: Education
Classifier: Programming Language :: Python :: 2
Classifier: Programming Language :: Python :: 3
Classifier: Operating System :: MacOS :: MacOS X
Classifier: Operating System :: Microsoft :: Windows
